zcts/__init__.py
zcts/a_small_test.py
zcts/cmd.py
zcts/zcts.py
zcts/zcts_unittest.py
zcts-0.0.6.dist-info/METADATA
zcts-0.0.6.dist-info/WHEEL
zcts-0.0.6.dist-info/top_level.txt
zcts-0.0.6.dist-info/RECORD
