Metadata-Version: 2.1
Name: zcts
Version: 0.0.6
Summary: ZD Converter 2000 python SDK
Home-page: https://github.com/Klareliebe7/zcts
Author: zhengkunli
Author-email: 1st.melchior@gmail.com
License: MIT
Platform: UNKNOWN
Classifier: Programming Language :: Python :: 3
Classifier: License :: OSI Approved :: MIT License
Classifier: Operating System :: OS Independent
Requires-Python: >=3.8.0
Requires-Dist: pyserial
Requires-Dist: colorama
